setup.py
ezexif/__init__.py
ezexif.egg-info/PKG-INFO
ezexif.egg-info/SOURCES.txt
ezexif.egg-info/dependency_links.txt
ezexif.egg-info/requires.txt
ezexif.egg-info/top_level.txt