Metadata-Version: 1.0
Name: ezexif
Version: 0.0.4
Summary: Wrapper for origin exifread.process_file
Home-page: https://wsgfz.cn
Author: wsgfz
Author-email: wsgfz.cn@gmail.com
License: UNKNOWN
Platform: UNKNOWN
